ApacheKudu140ZhongwenWendang/README.md
ApacheKudu140ZhongwenWendang/__init__.py
ApacheKudu140ZhongwenWendang/__main__.py
ApacheKudu140ZhongwenWendang/file.epub
ApacheKudu140ZhongwenWendang/index.html
ApacheKudu140ZhongwenWendang/css/__init__.py
ApacheKudu140ZhongwenWendang/css/annotations.css
ApacheKudu140ZhongwenWendang/css/main.css
ApacheKudu140ZhongwenWendang/css/normalize.css
ApacheKudu140ZhongwenWendang/css/popup.css
ApacheKudu140ZhongwenWendang/font/__init__.py
ApacheKudu140ZhongwenWendang/font/fontello.eot
ApacheKudu140ZhongwenWendang/font/fontello.svg
ApacheKudu140ZhongwenWendang/font/fontello.ttf
ApacheKudu140ZhongwenWendang/font/fontello.woff
ApacheKudu140ZhongwenWendang/img/__init__.py
ApacheKudu140ZhongwenWendang/img/annotator-glyph-sprite.png
ApacheKudu140ZhongwenWendang/img/annotator-icon-sprite.png
ApacheKudu140ZhongwenWendang/img/apple-touch-icon.png
ApacheKudu140ZhongwenWendang/img/cancelfullscreen.png
ApacheKudu140ZhongwenWendang/img/close.png
ApacheKudu140ZhongwenWendang/img/fullscreen.png
ApacheKudu140ZhongwenWendang/img/loader.gif
ApacheKudu140ZhongwenWendang/img/menu-icon.png
ApacheKudu140ZhongwenWendang/img/save.png
ApacheKudu140ZhongwenWendang/img/saved.png
ApacheKudu140ZhongwenWendang/img/settings-s.png
ApacheKudu140ZhongwenWendang/img/settings.png
ApacheKudu140ZhongwenWendang/img/star.png
ApacheKudu140ZhongwenWendang/js/__init__.py
ApacheKudu140ZhongwenWendang/js/epub.js
ApacheKudu140ZhongwenWendang/js/epub.min.js
ApacheKudu140ZhongwenWendang/js/epub.min.map
ApacheKudu140ZhongwenWendang/js/hooks.min.js
ApacheKudu140ZhongwenWendang/js/hooks.min.map
ApacheKudu140ZhongwenWendang/js/reader.js
ApacheKudu140ZhongwenWendang/js/reader.js.map
ApacheKudu140ZhongwenWendang/js/reader.min.js
ApacheKudu140ZhongwenWendang/js/reader.min.map
ApacheKudu140ZhongwenWendang/js/hooks/__init__.py
ApacheKudu140ZhongwenWendang/js/hooks/extensions/__init__.py
ApacheKudu140ZhongwenWendang/js/hooks/extensions/highlight.js
apache_kudu_1_4_0_zhongwen_wendang-2024.3.2.0.dist-info/METADATA
apache_kudu_1_4_0_zhongwen_wendang-2024.3.2.0.dist-info/WHEEL
apache_kudu_1_4_0_zhongwen_wendang-2024.3.2.0.dist-info/entry_points.txt
apache_kudu_1_4_0_zhongwen_wendang-2024.3.2.0.dist-info/top_level.txt
apache_kudu_1_4_0_zhongwen_wendang-2024.3.2.0.dist-info/RECORD
